singularity/__init__.py
singularity/config.py
singularity/db/__init__.py
singularity/db/mongo/__init__.py
singularity/db/mongo/main.py
singularity/db/mongo/model.py
singularity/db/mongo/types.py
singularity/db/postgres/__init__.py
singularity/db/postgres/main.py
singularity/db/postgres/models.py
singularity/db/postgres/schemas.py
singularity/db/postgres/transactional.py
singularity/exceptions/__init__.py
singularity/exceptions/cache_exceptions.py
singularity/exceptions/http_exceptions.py
singularity/exceptions/singularity.py
singularity/logger.py
singularity/main.py
singularity/middlewares/client_cache_middleware.py
singularity/schemas.py
singularity/service.py
singularity/setup.py
singularity/types.py
singularity/utils/__init__.py
singularity/utils/cache.py
singularity/utils/queue.py
singularity/utils/rate_limit.py
singularity_core-0.2.1.dist-info/METADATA
singularity_core-0.2.1.dist-info/WHEEL
singularity_core-0.2.1.dist-info/RECORD
