Metadata-Version: 2.1
Name: singularity-core
Version: 0.2.1
Summary: Funny backend
License: MIT
Author: Anandesh Sharma
Author-email: anandeshsharma@gmail.com
Requires-Python: >=3.10,<4.0
Classifier: License :: OSI Approved :: MIT License
Classifier: Programming Language :: Python :: 3
Classifier: Programming Language :: Python :: 3.10
Classifier: Programming Language :: Python :: 3.11
Classifier: Programming Language :: Python :: 3.12
Requires-Dist: aiomysql (>=0.2.0,<0.3.0)
Requires-Dist: alembic (>=1.13.1,<2.0.0)
Requires-Dist: asyncpg (>=0.29.0,<0.30.0)
Requires-Dist: beanie (>=1.26.0,<2.0.0)
Requires-Dist: celery (>=5.3.6,<6.0.0)
Requires-Dist: click (>=8.1.7,<9.0.0)
Requires-Dist: coverage (>=7.4.0,<8.0.0)
Requires-Dist: cryptography (>=41.0.7,<42.0.0)
Requires-Dist: fastapi-event (>=0.1.3,<0.2.0)
Requires-Dist: fastapi[standard] (>=0.112.0,<0.113.0)
Requires-Dist: gunicorn (>=21.2.0,<22.0.0)
Requires-Dist: httpx (>=0.26.0,<0.27.0)
Requires-Dist: motor (>=3.5.1,<4.0.0)
Requires-Dist: pydantic-settings (>=2.1.0,<3.0.0)
Requires-Dist: pyjwt (>=2.8.0,<3.0.0)
Requires-Dist: pytest-asyncio (>=0.23.3,<0.24.0)
Requires-Dist: pythondi (>=1.2.4,<2.0.0)
Requires-Dist: redis (>=5.0.1,<6.0.0)
Requires-Dist: sqlalchemy[asyncio] (>=2.0.25,<3.0.0)
Requires-Dist: ujson (>=5.9.0,<6.0.0)
Requires-Dist: uvicorn (>=0.25.0,<0.26.0)
